regexpro/__init__.py
regexpro/validate.py
validate/__init__.py
validate/user.py
regexpro-0.1.1.dist-info/LICENSE
regexpro-0.1.1.dist-info/METADATA
regexpro-0.1.1.dist-info/WHEEL
regexpro-0.1.1.dist-info/top_level.txt
regexpro-0.1.1.dist-info/RECORD
